mcp_lark_doc_manage/__init__.py
mcp_lark_doc_manage/__main__.py
mcp_lark_doc_manage/markdown_converter.py
mcp_lark_doc_manage/server.py
mcp_lark_doc_manage-0.1.8.dist-info/LICENSE
mcp_lark_doc_manage-0.1.8.dist-info/METADATA
mcp_lark_doc_manage-0.1.8.dist-info/WHEEL
mcp_lark_doc_manage-0.1.8.dist-info/entry_points.txt
mcp_lark_doc_manage-0.1.8.dist-info/top_level.txt
mcp_lark_doc_manage-0.1.8.dist-info/RECORD
