Metadata-Version: 2.1
Name: mcp-lark-doc-manage
Version: 0.1.8
Summary: A Model Context Protocol server for accessing Lark documents
Author: Xeonice
License: MIT
Classifier: Development Status :: 4 - Beta
Classifier: Intended Audience :: Developers
Classifier: License :: OSI Approved :: MIT License
Classifier: Programming Language :: Python :: 3
Classifier: Programming Language :: Python :: 3.10
Requires-Python: >=3.7
License-File: LICENSE
Requires-Dist: httpx (>=0.28.1)
Requires-Dist: mcp[cli] (>=1.3.0)
Requires-Dist: lark-oapi (>=1.0.0)
Requires-Dist: aiohttp (>=3.9.0)
Requires-Dist: mistune (>=2.0.0)
Provides-Extra: dev
Requires-Dist: pyright (>=1.1.389) ; extra == 'dev'
Requires-Dist: ruff (>=0.7.3) ; extra == 'dev'
Requires-Dist: pytest (>=8.0.0) ; extra == 'dev'
Requires-Dist: pytest-asyncio (>=0.23.0) ; extra == 'dev'
Requires-Dist: pytest-cov (>=4.1.0) ; extra == 'dev'
